shipyard_ftp/__init__.py
shipyard_ftp/cli/__init__.py
shipyard_ftp/cli/authtest.py
shipyard_ftp/cli/delete.py
shipyard_ftp/cli/download.py
shipyard_ftp/cli/move.py
shipyard_ftp/cli/upload.py
shipyard_ftp/exceptions.py
shipyard_ftp/ftp.py
shipyard_ftp-0.2.2.dist-info/METADATA
shipyard_ftp-0.2.2.dist-info/WHEEL
shipyard_ftp-0.2.2.dist-info/RECORD
